dynoscale/__init__.py
dynoscale/agent.py
dynoscale/asgi.py
dynoscale/config.py
dynoscale/constants.py
dynoscale/permadict.py
dynoscale/publisher.py
dynoscale/repository.py
dynoscale/utils.py
dynoscale/uvicorn.py
dynoscale/version.py
dynoscale/wsgi.py
dynoscale/hooks/__init__.py
dynoscale/hooks/gunicorn.py
dynoscale/workers/__init__.py
dynoscale/workers/rq_logger.py
dynoscale-1.2.2.dist-info/LICENSE
dynoscale-1.2.2.dist-info/METADATA
dynoscale-1.2.2.dist-info/WHEEL
dynoscale-1.2.2.dist-info/top_level.txt
dynoscale-1.2.2.dist-info/RECORD
