Metadata-Version: 2.1
Name: dynoscale
Version: 1.2.2
Summary: A simple yet efficient scaling agent for Python apps on Heroku
Home-page: https://dynoscale.net
Author: Ondrej Dolejsi
Author-email: ondrej.dolejsi@gmail.com
License: MIT
Project-URL: Documentation, http://dynoscale.net/documentation/category/general
Project-URL: Source, https://github.com/Mjolnir-Software/dynoscale-python
Project-URL: Tracker, https://github.com/Mjolnir-Software/dynoscale-python
Keywords: heroku,scaling,dyno,wsgi
Classifier: Development Status :: 5 - Production/Stable
Classifier: Programming Language :: Python
Classifier: Programming Language :: Python :: 3 :: Only
Classifier: Programming Language :: Python :: 3.10
Classifier: Programming Language :: Python :: 3.11
Classifier: License :: OSI Approved :: MIT License
Classifier: Natural Language :: English
Classifier: Intended Audience :: Developers
Classifier: Intended Audience :: Information Technology
Classifier: Operating System :: Unix
Classifier: Operating System :: POSIX :: BSD
Classifier: Operating System :: POSIX :: Linux
Classifier: Operating System :: MacOS :: MacOS X
Classifier: Topic :: Adaptive Technologies
Classifier: Topic :: Internet
Classifier: Topic :: Internet :: Log Analysis
Classifier: Topic :: Internet :: WWW/HTTP
Classifier: Topic :: Internet :: WWW/HTTP :: HTTP Servers
Classifier: Topic :: Internet :: WWW/HTTP :: Site Management
Classifier: Topic :: Internet :: WWW/HTTP :: WSGI
Classifier: Topic :: Internet :: WWW/HTTP :: WSGI :: Application
Classifier: Topic :: Internet :: WWW/HTTP :: WSGI :: Middleware
Classifier: Topic :: Internet :: WWW/HTTP :: WSGI :: Server
Classifier: Topic :: Software Development :: Libraries
Classifier: Topic :: Software Development :: Libraries :: Python Modules
Classifier: Topic :: Software Development :: Pre-processors
Classifier: Topic :: System :: Logging
Classifier: Topic :: System :: Monitoring
Classifier: Topic :: System :: Networking :: Monitoring
Requires-Python: >=3.10
Provides-Extra: test
License-File: LICENSE
